odoo10_addon_base_import_security_group-10.0.1.0.0.99.dev7-nspkg.pth
odoo/addons/base_import_security_group/README.rst
odoo/addons/base_import_security_group/__init__.py
odoo/addons/base_import_security_group/__manifest__.py
odoo/addons/base_import_security_group/i18n/base_import_security_group.pot
odoo/addons/base_import_security_group/i18n/ca.po
odoo/addons/base_import_security_group/i18n/de.po
odoo/addons/base_import_security_group/i18n/es.po
odoo/addons/base_import_security_group/i18n/fr.po
odoo/addons/base_import_security_group/i18n/gl.po
odoo/addons/base_import_security_group/i18n/hr.po
odoo/addons/base_import_security_group/i18n/it.po
odoo/addons/base_import_security_group/i18n/pt.po
odoo/addons/base_import_security_group/i18n/sk.po
odoo/addons/base_import_security_group/models/__init__.py
odoo/addons/base_import_security_group/models/models.py
odoo/addons/base_import_security_group/security/base_import_security_group_security.xml
odoo/addons/base_import_security_group/static/description/icon.png
odoo/addons/base_import_security_group/static/description/icon.svg
odoo/addons/base_import_security_group/static/src/js/import.js
odoo/addons/base_import_security_group/tests/__init__.py
odoo/addons/base_import_security_group/tests/test_base_import_security_group.py
odoo/addons/base_import_security_group/views/base_import.xml
odoo10_addon_base_import_security_group-10.0.1.0.0.99.dev7.dist-info/METADATA
odoo10_addon_base_import_security_group-10.0.1.0.0.99.dev7.dist-info/WHEEL
odoo10_addon_base_import_security_group-10.0.1.0.0.99.dev7.dist-info/namespace_packages.txt
odoo10_addon_base_import_security_group-10.0.1.0.0.99.dev7.dist-info/top_level.txt
odoo10_addon_base_import_security_group-10.0.1.0.0.99.dev7.dist-info/RECORD
