Metadata-Version: 2.1
Name: odoo10-addon-base-import-security-group
Version: 10.0.1.0.0.99.dev7
Summary: Group-based permissions for importing CSV files
Home-page: http://odoo-community.org
Author: Odoo Community Association (OCA), Alejandro Santana <alejandrosantana@anubia.es>, Onestein
Author-email: support@odoo-community.org
License: AGPL-3
Platform: UNKNOWN
Classifier: Programming Language :: Python
Classifier: Framework :: Odoo
Classifier: License :: OSI Approved :: GNU Affero General Public License v3
Requires-Python: ~=2.7
Requires-Dist: odoo (<10.1dev,>=10.0)
